jaxincell/__init__.py
jaxincell/__main__.py
jaxincell/_algorithms.py
jaxincell/_boundary_conditions.py
jaxincell/_constants.py
jaxincell/_diagnostics.py
jaxincell/_fields.py
jaxincell/_particles.py
jaxincell/_plot.py
jaxincell/_simulation.py
jaxincell/_sources.py
jaxincell/version.py
jaxincell-0.6.dist-info/licenses/LICENSE
jaxincell-0.6.dist-info/METADATA
jaxincell-0.6.dist-info/WHEEL
jaxincell-0.6.dist-info/entry_points.txt
jaxincell-0.6.dist-info/top_level.txt
jaxincell-0.6.dist-info/RECORD
