Metadata-Version: 2.4
Name: jaxincell
Version: 0.6
Summary: JAX-in-Cell: Particle-in-Cell code in JAX
Author-email: "UWPlasma, UW-Madison group" <rogerio.jorge@wisc.edu>
License: MIT License
Project-URL: Homepage, https://github.com/uwplasma/JAX-in-Cell
Keywords: Plasma,Physics,Simulation,JAX
Classifier: Development Status :: 3 - Alpha
Classifier: Operating System :: OS Independent
Classifier: License :: OSI Approved :: MIT License
Classifier: Programming Language :: Python :: 3
Requires-Python: >=3.5
License-File: LICENSE
Requires-Dist: jax
Requires-Dist: jaxlib
Requires-Dist: jax_tqdm
Requires-Dist: matplotlib
Dynamic: license-file
